MANIFEST.in
README.txt
setup.cfg
setup.py
collective/__init__.py
collective.lti.egg-info/PKG-INFO
collective.lti.egg-info/SOURCES.txt
collective.lti.egg-info/dependency_links.txt
collective.lti.egg-info/entry_points.txt
collective.lti.egg-info/namespace_packages.txt
collective.lti.egg-info/not-zip-safe
collective.lti.egg-info/requires.txt
collective.lti.egg-info/top_level.txt
collective/lti/__init__.py
collective/lti/config.py
collective/lti/configure.zcml
collective/lti/interfaces.py
collective/lti/setuphandlers.py
collective/lti/tests.py
collective/lti/browser/__init__.py
collective/lti/browser/config.pt
collective/lti/browser/configure.zcml
collective/lti/browser/lpview.pt
collective/lti/browser/lti.py
collective/lti/browser/ltierror.pt
collective/lti/browser/ltimanage.py
collective/lti/browser/ltimanageresults.pt
collective/lti/browser/ltiview.pt
collective/lti/content/__init__.py
collective/lti/content/launchfolder.py
collective/lti/content/ltilaunch.py
collective/lti/locales/collective.lti.pot
collective/lti/locales/es/LC_MESSAGES/collective.lti.mo
collective/lti/locales/es/LC_MESSAGES/collective.lti.po
collective/lti/profiles/default/actions.xml
collective/lti/profiles/default/browserlayer.xml
collective/lti/profiles/default/collective_lti_setup.txt
collective/lti/profiles/default/factorytool.xml
collective/lti/profiles/default/import_steps.xml
collective/lti/profiles/default/metadata.xml
collective/lti/profiles/default/types.xml
collective/lti/profiles/default/types/LaunchFolder.xml
collective/lti/profiles/default/types/LtiLaunchParams.xml
collective/lti/resources/ltiexport.png
docs/HISTORY.txt
docs/INSTALL.txt
docs/LICENSE.GPL
docs/LICENSE.txt