Metadata-Version: 1.1
Name: collective.lti
Version: 1.0
Summary: Implementation of LTI in Plone
Home-page: http://svn.plone.org/svn/collective/
Author: Brent Lambert
Author-email: brent@enpraxis.net
License: GPL
Keywords: lti
Platform: UNKNOWN
Classifier: Framework :: Plone
Classifier: Programming Language :: Python
